[{"lat":50.52291,"lng":30.498885,"title":"Героев Днепра 1"},{"lat":50.52239,"lng":30.498842,"title":"Героев Днепра 2"},{"lat":50.511594,"lng":30.497866,"title":"Минская 1"},{"lat":50.511519,"lng":30.499271,"title":"Минская 2"},{"lat":50.51286,"lng":30.499341,"title":"Минская 3"},{"lat":50.512908,"lng":30.49789,"title":"Минская 4"},{"lat":50.502232,"lng":30.497643,"title":"Оболонь 1"},{"lat":50.502205,"lng":30.498903,"title":"Оболонь 2"},{"lat":50.500736,"lng":30.498979,"title":"Оболонь 3"},{"lat":50.487033,"lng":30.498331,"title":"Петровка 1"},{"lat":50.473561,"lng":30.504825,"title":"Тараса Шевченко 1"},{"lat":50.466454,"lng":30.513858,"title":"Контрактова 1"},{"lat":50.465133,"lng":30.516253,"title":"Контрактова 2"},{"lat":50.458948,"lng":30.525059,"title":"Почтовая 1"},{"lat":50.449794,"lng":30.524388,"title":"Майдан 1"},{"lat":50.439612,"lng":30.516979,"title":"Льва Толстого 1"},{"lat":50.432191,"lng":30.516497,"title":"Олимпийская 1"},{"lat":50.420631,"lng":30.520901,"title":"Дворец Украины 1"},{"lat":50.412501,"lng":30.523804,"title":"Лыбедская 1"},{"lat":50.413207,"lng":30.525501,"title":"Лыбедская 2"},{"lat":50.404667,"lng":30.516362,"title":"Демеевская 1"},{"lat":50.40453,"lng":30.517435,"title":"Демеевская 2"},{"lat":50.405531,"lng":30.5169,"title":"Демеевская 3"},{"lat":50.405223,"lng":30.517941,"title":"Демеевская 4"},{"lat":50.397639,"lng":30.508373,"title":"Голосеевская 1"},{"lat":50.397303,"lng":30.509393,"title":"Голосеевская 2"},{"lat":50.397947,"lng":30.509566,"title":"Голосеевская 3"},{"lat":50.393131,"lng":30.487538,"title":"Васильковская 1"},{"lat":50.393446,"lng":30.489514,"title":"Васильковская 2"},{"lat":50.381528,"lng":30.476984,"title":"Выставочный центр 1"},{"lat":50.376079,"lng":30.467484,"title":"Ипподром 1"},{"lat":50.47645,"lng":30.43084,"title":"Сырец 1"},{"lat":50.47365,"lng":30.448768,"title":"Дорогожичи 1"},{"lat":50.462334,"lng":30.481945,"title":"Лукьяновская 1"},{"lat":50.44838,"lng":30.513818,"title":"Золотые ворота 1"},{"lat":50.43794,"lng":30.520937,"title":"Дворец спорта 1"},{"lat":50.436938,"lng":30.531877,"title":"Кловская 1"},{"lat":50.427274,"lng":30.538642,"title":"Печерская 1"},{"lat":50.427905,"lng":30.539665,"title":"Печерская 2"},{"lat":50.41845,"lng":30.544553,"title":"Дружбы народов 1"},{"lat":50.417858,"lng":30.544982,"title":"Дружбы народов 2"},{"lat":50.401319,"lng":30.561585,"title":"Выдубичи 1"},{"lat":50.394167,"lng":30.604371,"title":"Славутич 1"},{"lat":50.395671,"lng":30.616939,"title":"Осокорки 1"},{"lat":50.395397,"lng":30.61527,"title":"Осокорки 2"},{"lat":50.397911,"lng":30.633365,"title":"Позняки 1"},{"lat":50.398131,"lng":30.635605,"title":"Позняки 2"},{"lat":50.400658,"lng":30.651319,"title":"Харьковская 1"},{"lat":50.40096,"lng":30.653103,"title":"Харьковская 2"},{"lat":50.403088,"lng":30.666021,"title":"Вырлица 1"},{"lat":50.403264,"lng":30.683028,"title":"Бориспольская 1"},{"lat":50.409798,"lng":30.696902,"title":"Красный хутор 1"},{"lat":50.465604,"lng":30.354867,"title":"Академгородок 1"},{"lat":50.464152,"lng":30.354952,"title":"Академгородок 2"},{"lat":50.465604,"lng":30.355884,"title":"Академгородок 3"},{"lat":50.464235,"lng":30.356013,"title":"Академгородок 4"},{"lat":50.455923,"lng":30.364645,"title":"Житомирская 1"},{"lat":50.457704,"lng":30.391835,"title":"Святошин 1"},{"lat":50.457704,"lng":30.38838,"title":"Святошин 2"},{"lat":50.459391,"lng":30.405875,"title":"Нивки 1"},{"lat":50.458459,"lng":30.403128,"title":"Нивки 2"},{"lat":50.458569,"lng":30.421217,"title":"Берестейская 1"},{"lat":50.454897,"lng":30.44533,"title":"Шулявская 1"},{"lat":50.450684,"lng":30.466195,"title":"Политехнический институт 1"},{"lat":50.441669,"lng":30.487897,"title":"Вокзальная 1"},{"lat":50.444309,"lng":30.505864,"title":"Университет 1"},{"lat":50.445233,"lng":30.517818,"title":"Театральная 1"},{"lat":50.447567,"lng":30.528786,"title":"Хрещатик 1"},{"lat":50.447156,"lng":30.522651,"title":"Хрещатик 2"},{"lat":50.444252,"lng":30.545337,"title":"Арсенальная 1"},{"lat":50.440963,"lng":30.558769,"title":"Днепр 1"},{"lat":50.446089,"lng":30.576856,"title":"Гидропарк 1"},{"lat":50.451427,"lng":30.597474,"title":"Левобережная 1"},{"lat":50.451838,"lng":30.599194,"title":"Левобережная 2"},{"lat":50.45562,"lng":30.613085,"title":"Дарница 1"},{"lat":50.456634,"lng":30.613986,"title":"Дарница 2"},{"lat":50.459808,"lng":30.630326,"title":"Чениговская 1"},{"lat":50.464896,"lng":30.643714,"title":"Лесная 1"},{"lat":50.464184,"lng":30.644403,"title":"Лесная 2"},{"lat":50.465444,"lng":30.64592,"title":"Лесная 3"}]